bmdb/__init__.py
bmdb/cli.py
bmdb-1.3.1.dist-info/METADATA
bmdb-1.3.1.dist-info/WHEEL
bmdb-1.3.1.dist-info/entry_points.txt
bmdb-1.3.1.dist-info/top_level.txt
bmdb-1.3.1.dist-info/RECORD
